[
  {
    "rank": 1,
    "route_id": "R001",
    "from_node_id": "N003",
    "to_node_id": "N019",
    "estimated_flow": 5346220.0,
    "distance_saving_km": 0.0,
    "total_screen_cost": 0.0,
    "economic_score": 0.0,
    "summary": {
      "label": "MVP 예비 경제성 점수",
      "status": "failed",
      "straight_distance_km": 19.216,
      "assumed_existing_route_length_km": 24.981,
      "route_length_km": 0.0,
      "distance_saving_km": 0.0,
      "benefit_proxy": 0.0,
      "cost_per_flow_saving": null,
      "surface_road_length_km": 0.0,
      "existing_road_length_km": 0.0,
      "existing_tunnel_length_km": 0.0,
      "new_surface_road_length_km": 0.0,
      "tunnel_length_km": 0.0,
      "bridge_length_km": 0.0,
      "existing_road_access_length_km": 0.0,
      "existing_road_access_percent": 0.0,
      "route_generation_method": "failed",
      "river_crossing_count": 0,
      "failed_reason": "connection timeout expired\nMultiple connection attempts failed. All failures were:\n- host: 'localhost', port: '5432', hostaddr: '::1': connection timeout expired\n- host: 'localhost', port: '5432', hostaddr: '127.0.0.1': connection timeout expired"
    }
  },
  {
    "rank": 2,
    "route_id": "R002",
    "from_node_id": "N018",
    "to_node_id": "N031",
    "estimated_flow": 3257329.0,
    "distance_saving_km": 0.0,
    "total_screen_cost": 0.0,
    "economic_score": 0.0,
    "summary": {
      "label": "MVP 예비 경제성 점수",
      "status": "failed",
      "straight_distance_km": 37.797,
      "assumed_existing_route_length_km": 49.136,
      "route_length_km": 0.0,
      "distance_saving_km": 0.0,
      "benefit_proxy": 0.0,
      "cost_per_flow_saving": null,
      "surface_road_length_km": 0.0,
      "existing_road_length_km": 0.0,
      "existing_tunnel_length_km": 0.0,
      "new_surface_road_length_km": 0.0,
      "tunnel_length_km": 0.0,
      "bridge_length_km": 0.0,
      "existing_road_access_length_km": 0.0,
      "existing_road_access_percent": 0.0,
      "route_generation_method": "failed",
      "river_crossing_count": 0,
      "failed_reason": "connection timeout expired\nMultiple connection attempts failed. All failures were:\n- host: 'localhost', port: '5432', hostaddr: '::1': connection timeout expired\n- host: 'localhost', port: '5432', hostaddr: '127.0.0.1': connection timeout expired"
    }
  },
  {
    "rank": 3,
    "route_id": "R003",
    "from_node_id": "N036",
    "to_node_id": "N054",
    "estimated_flow": 892774.8,
    "distance_saving_km": 0.0,
    "total_screen_cost": 0.0,
    "economic_score": 0.0,
    "summary": {
      "label": "MVP 예비 경제성 점수",
      "status": "failed",
      "straight_distance_km": 14.216,
      "assumed_existing_route_length_km": 18.481,
      "route_length_km": 0.0,
      "distance_saving_km": 0.0,
      "benefit_proxy": 0.0,
      "cost_per_flow_saving": null,
      "surface_road_length_km": 0.0,
      "existing_road_length_km": 0.0,
      "existing_tunnel_length_km": 0.0,
      "new_surface_road_length_km": 0.0,
      "tunnel_length_km": 0.0,
      "bridge_length_km": 0.0,
      "existing_road_access_length_km": 0.0,
      "existing_road_access_percent": 0.0,
      "route_generation_method": "failed",
      "river_crossing_count": 0,
      "failed_reason": "connection timeout expired\nMultiple connection attempts failed. All failures were:\n- host: 'localhost', port: '5432', hostaddr: '::1': connection timeout expired\n- host: 'localhost', port: '5432', hostaddr: '127.0.0.1': connection timeout expired"
    }
  },
  {
    "rank": 4,
    "route_id": "R004",
    "from_node_id": "N002",
    "to_node_id": "N006",
    "estimated_flow": 888528.8,
    "distance_saving_km": 0.0,
    "total_screen_cost": 0.0,
    "economic_score": 0.0,
    "summary": {
      "label": "MVP 예비 경제성 점수",
      "status": "failed",
      "straight_distance_km": 8.856,
      "assumed_existing_route_length_km": 11.513,
      "route_length_km": 0.0,
      "distance_saving_km": 0.0,
      "benefit_proxy": 0.0,
      "cost_per_flow_saving": null,
      "surface_road_length_km": 0.0,
      "existing_road_length_km": 0.0,
      "existing_tunnel_length_km": 0.0,
      "new_surface_road_length_km": 0.0,
      "tunnel_length_km": 0.0,
      "bridge_length_km": 0.0,
      "existing_road_access_length_km": 0.0,
      "existing_road_access_percent": 0.0,
      "route_generation_method": "failed",
      "river_crossing_count": 0,
      "failed_reason": "connection timeout expired\nMultiple connection attempts failed. All failures were:\n- host: 'localhost', port: '5432', hostaddr: '::1': connection timeout expired\n- host: 'localhost', port: '5432', hostaddr: '127.0.0.1': connection timeout expired"
    }
  },
  {
    "rank": 5,
    "route_id": "R005",
    "from_node_id": "N001",
    "to_node_id": "N010",
    "estimated_flow": 640911.2,
    "distance_saving_km": 0.0,
    "total_screen_cost": 0.0,
    "economic_score": 0.0,
    "summary": {
      "label": "MVP 예비 경제성 점수",
      "status": "failed",
      "straight_distance_km": 18.491,
      "assumed_existing_route_length_km": 24.038,
      "route_length_km": 0.0,
      "distance_saving_km": 0.0,
      "benefit_proxy": 0.0,
      "cost_per_flow_saving": null,
      "surface_road_length_km": 0.0,
      "existing_road_length_km": 0.0,
      "existing_tunnel_length_km": 0.0,
      "new_surface_road_length_km": 0.0,
      "tunnel_length_km": 0.0,
      "bridge_length_km": 0.0,
      "existing_road_access_length_km": 0.0,
      "existing_road_access_percent": 0.0,
      "route_generation_method": "failed",
      "river_crossing_count": 0,
      "failed_reason": "connection timeout expired\nMultiple connection attempts failed. All failures were:\n- host: 'localhost', port: '5432', hostaddr: '::1': connection timeout expired\n- host: 'localhost', port: '5432', hostaddr: '127.0.0.1': connection timeout expired"
    }
  },
  {
    "rank": 6,
    "route_id": "R006",
    "from_node_id": "N025",
    "to_node_id": "N031",
    "estimated_flow": 570756.2,
    "distance_saving_km": 0.0,
    "total_screen_cost": 0.0,
    "economic_score": 0.0,
    "summary": {
      "label": "MVP 예비 경제성 점수",
      "status": "failed",
      "straight_distance_km": 5.116,
      "assumed_existing_route_length_km": 6.651,
      "route_length_km": 0.0,
      "distance_saving_km": 0.0,
      "benefit_proxy": 0.0,
      "cost_per_flow_saving": null,
      "surface_road_length_km": 0.0,
      "existing_road_length_km": 0.0,
      "existing_tunnel_length_km": 0.0,
      "new_surface_road_length_km": 0.0,
      "tunnel_length_km": 0.0,
      "bridge_length_km": 0.0,
      "existing_road_access_length_km": 0.0,
      "existing_road_access_percent": 0.0,
      "route_generation_method": "failed",
      "river_crossing_count": 0,
      "failed_reason": "connection timeout expired\nMultiple connection attempts failed. All failures were:\n- host: 'localhost', port: '5432', hostaddr: '::1': connection timeout expired\n- host: 'localhost', port: '5432', hostaddr: '127.0.0.1': connection timeout expired"
    }
  },
  {
    "rank": 7,
    "route_id": "R007",
    "from_node_id": "N010",
    "to_node_id": "N021",
    "estimated_flow": 538073.2,
    "distance_saving_km": 0.0,
    "total_screen_cost": 0.0,
    "economic_score": 0.0,
    "summary": {
      "label": "MVP 예비 경제성 점수",
      "status": "failed",
      "straight_distance_km": 23.964,
      "assumed_existing_route_length_km": 31.153,
      "route_length_km": 0.0,
      "distance_saving_km": 0.0,
      "benefit_proxy": 0.0,
      "cost_per_flow_saving": null,
      "surface_road_length_km": 0.0,
      "existing_road_length_km": 0.0,
      "existing_tunnel_length_km": 0.0,
      "new_surface_road_length_km": 0.0,
      "tunnel_length_km": 0.0,
      "bridge_length_km": 0.0,
      "existing_road_access_length_km": 0.0,
      "existing_road_access_percent": 0.0,
      "route_generation_method": "failed",
      "river_crossing_count": 0,
      "failed_reason": "connection timeout expired\nMultiple connection attempts failed. All failures were:\n- host: 'localhost', port: '5432', hostaddr: '::1': connection timeout expired\n- host: 'localhost', port: '5432', hostaddr: '127.0.0.1': connection timeout expired"
    }
  },
  {
    "rank": 8,
    "route_id": "R008",
    "from_node_id": "N020",
    "to_node_id": "N032",
    "estimated_flow": 496889.0,
    "distance_saving_km": 0.0,
    "total_screen_cost": 0.0,
    "economic_score": 0.0,
    "summary": {
      "label": "MVP 예비 경제성 점수",
      "status": "failed",
      "straight_distance_km": 18.756,
      "assumed_existing_route_length_km": 24.383,
      "route_length_km": 0.0,
      "distance_saving_km": 0.0,
      "benefit_proxy": 0.0,
      "cost_per_flow_saving": null,
      "surface_road_length_km": 0.0,
      "existing_road_length_km": 0.0,
      "existing_tunnel_length_km": 0.0,
      "new_surface_road_length_km": 0.0,
      "tunnel_length_km": 0.0,
      "bridge_length_km": 0.0,
      "existing_road_access_length_km": 0.0,
      "existing_road_access_percent": 0.0,
      "route_generation_method": "failed",
      "river_crossing_count": 0,
      "failed_reason": "connection timeout expired\nMultiple connection attempts failed. All failures were:\n- host: 'localhost', port: '5432', hostaddr: '::1': connection timeout expired\n- host: 'localhost', port: '5432', hostaddr: '127.0.0.1': connection timeout expired"
    }
  },
  {
    "rank": 9,
    "route_id": "R009",
    "from_node_id": "N022",
    "to_node_id": "N024",
    "estimated_flow": 469066.0,
    "distance_saving_km": 0.0,
    "total_screen_cost": 0.0,
    "economic_score": 0.0,
    "summary": {
      "label": "MVP 예비 경제성 점수",
      "status": "failed",
      "straight_distance_km": 12.321,
      "assumed_existing_route_length_km": 16.017,
      "route_length_km": 0.0,
      "distance_saving_km": 0.0,
      "benefit_proxy": 0.0,
      "cost_per_flow_saving": null,
      "surface_road_length_km": 0.0,
      "existing_road_length_km": 0.0,
      "existing_tunnel_length_km": 0.0,
      "new_surface_road_length_km": 0.0,
      "tunnel_length_km": 0.0,
      "bridge_length_km": 0.0,
      "existing_road_access_length_km": 0.0,
      "existing_road_access_percent": 0.0,
      "route_generation_method": "failed",
      "river_crossing_count": 0,
      "failed_reason": "connection timeout expired\nMultiple connection attempts failed. All failures were:\n- host: 'localhost', port: '5432', hostaddr: '::1': connection timeout expired\n- host: 'localhost', port: '5432', hostaddr: '127.0.0.1': connection timeout expired"
    }
  },
  {
    "rank": 10,
    "route_id": "R010",
    "from_node_id": "N009",
    "to_node_id": "N037",
    "estimated_flow": 451259.6,
    "distance_saving_km": 0.0,
    "total_screen_cost": 0.0,
    "economic_score": 0.0,
    "summary": {
      "label": "MVP 예비 경제성 점수",
      "status": "failed",
      "straight_distance_km": 8.012,
      "assumed_existing_route_length_km": 10.416,
      "route_length_km": 0.0,
      "distance_saving_km": 0.0,
      "benefit_proxy": 0.0,
      "cost_per_flow_saving": null,
      "surface_road_length_km": 0.0,
      "existing_road_length_km": 0.0,
      "existing_tunnel_length_km": 0.0,
      "new_surface_road_length_km": 0.0,
      "tunnel_length_km": 0.0,
      "bridge_length_km": 0.0,
      "existing_road_access_length_km": 0.0,
      "existing_road_access_percent": 0.0,
      "route_generation_method": "failed",
      "river_crossing_count": 0,
      "failed_reason": "connection timeout expired\nMultiple connection attempts failed. All failures were:\n- host: 'localhost', port: '5432', hostaddr: '::1': connection timeout expired\n- host: 'localhost', port: '5432', hostaddr: '127.0.0.1': connection timeout expired"
    }
  },
  {
    "rank": 11,
    "route_id": "R011",
    "from_node_id": "N011",
    "to_node_id": "N022",
    "estimated_flow": 445002.6,
    "distance_saving_km": 0.0,
    "total_screen_cost": 0.0,
    "economic_score": 0.0,
    "summary": {
      "label": "MVP 예비 경제성 점수",
      "status": "failed",
      "straight_distance_km": 14.262,
      "assumed_existing_route_length_km": 18.541,
      "route_length_km": 0.0,
      "distance_saving_km": 0.0,
      "benefit_proxy": 0.0,
      "cost_per_flow_saving": null,
      "surface_road_length_km": 0.0,
      "existing_road_length_km": 0.0,
      "existing_tunnel_length_km": 0.0,
      "new_surface_road_length_km": 0.0,
      "tunnel_length_km": 0.0,
      "bridge_length_km": 0.0,
      "existing_road_access_length_km": 0.0,
      "existing_road_access_percent": 0.0,
      "route_generation_method": "failed",
      "river_crossing_count": 0,
      "failed_reason": "connection timeout expired\nMultiple connection attempts failed. All failures were:\n- host: 'localhost', port: '5432', hostaddr: '::1': connection timeout expired\n- host: 'localhost', port: '5432', hostaddr: '127.0.0.1': connection timeout expired"
    }
  },
  {
    "rank": 12,
    "route_id": "R012",
    "from_node_id": "N023",
    "to_node_id": "N040",
    "estimated_flow": 422263.4,
    "distance_saving_km": 0.0,
    "total_screen_cost": 0.0,
    "economic_score": 0.0,
    "summary": {
      "label": "MVP 예비 경제성 점수",
      "status": "failed",
      "straight_distance_km": 5.607,
      "assumed_existing_route_length_km": 7.289,
      "route_length_km": 0.0,
      "distance_saving_km": 0.0,
      "benefit_proxy": 0.0,
      "cost_per_flow_saving": null,
      "surface_road_length_km": 0.0,
      "existing_road_length_km": 0.0,
      "existing_tunnel_length_km": 0.0,
      "new_surface_road_length_km": 0.0,
      "tunnel_length_km": 0.0,
      "bridge_length_km": 0.0,
      "existing_road_access_length_km": 0.0,
      "existing_road_access_percent": 0.0,
      "route_generation_method": "failed",
      "river_crossing_count": 0,
      "failed_reason": "connection timeout expired\nMultiple connection attempts failed. All failures were:\n- host: 'localhost', port: '5432', hostaddr: '::1': connection timeout expired\n- host: 'localhost', port: '5432', hostaddr: '127.0.0.1': connection timeout expired"
    }
  },
  {
    "rank": 13,
    "route_id": "R013",
    "from_node_id": "N003",
    "to_node_id": "N007",
    "estimated_flow": 386837.6,
    "distance_saving_km": 0.0,
    "total_screen_cost": 0.0,
    "economic_score": 0.0,
    "summary": {
      "label": "MVP 예비 경제성 점수",
      "status": "failed",
      "straight_distance_km": 14.554,
      "assumed_existing_route_length_km": 18.92,
      "route_length_km": 0.0,
      "distance_saving_km": 0.0,
      "benefit_proxy": 0.0,
      "cost_per_flow_saving": null,
      "surface_road_length_km": 0.0,
      "existing_road_length_km": 0.0,
      "existing_tunnel_length_km": 0.0,
      "new_surface_road_length_km": 0.0,
      "tunnel_length_km": 0.0,
      "bridge_length_km": 0.0,
      "existing_road_access_length_km": 0.0,
      "existing_road_access_percent": 0.0,
      "route_generation_method": "failed",
      "river_crossing_count": 0,
      "failed_reason": "connection timeout expired\nMultiple connection attempts failed. All failures were:\n- host: 'localhost', port: '5432', hostaddr: '::1': connection timeout expired\n- host: 'localhost', port: '5432', hostaddr: '127.0.0.1': connection timeout expired"
    }
  },
  {
    "rank": 14,
    "route_id": "R014",
    "from_node_id": "N041",
    "to_node_id": "N049",
    "estimated_flow": 385522.0,
    "distance_saving_km": 0.0,
    "total_screen_cost": 0.0,
    "economic_score": 0.0,
    "summary": {
      "label": "MVP 예비 경제성 점수",
      "status": "failed",
      "straight_distance_km": 18.367,
      "assumed_existing_route_length_km": 23.877,
      "route_length_km": 0.0,
      "distance_saving_km": 0.0,
      "benefit_proxy": 0.0,
      "cost_per_flow_saving": null,
      "surface_road_length_km": 0.0,
      "existing_road_length_km": 0.0,
      "existing_tunnel_length_km": 0.0,
      "new_surface_road_length_km": 0.0,
      "tunnel_length_km": 0.0,
      "bridge_length_km": 0.0,
      "existing_road_access_length_km": 0.0,
      "existing_road_access_percent": 0.0,
      "route_generation_method": "failed",
      "river_crossing_count": 0,
      "failed_reason": "connection timeout expired\nMultiple connection attempts failed. All failures were:\n- host: 'localhost', port: '5432', hostaddr: '::1': connection timeout expired\n- host: 'localhost', port: '5432', hostaddr: '127.0.0.1': connection timeout expired"
    }
  },
  {
    "rank": 15,
    "route_id": "R015",
    "from_node_id": "N004",
    "to_node_id": "N031",
    "estimated_flow": 372694.2,
    "distance_saving_km": 0.0,
    "total_screen_cost": 0.0,
    "economic_score": 0.0,
    "summary": {
      "label": "MVP 예비 경제성 점수",
      "status": "failed",
      "straight_distance_km": 9.668,
      "assumed_existing_route_length_km": 12.568,
      "route_length_km": 0.0,
      "distance_saving_km": 0.0,
      "benefit_proxy": 0.0,
      "cost_per_flow_saving": null,
      "surface_road_length_km": 0.0,
      "existing_road_length_km": 0.0,
      "existing_tunnel_length_km": 0.0,
      "new_surface_road_length_km": 0.0,
      "tunnel_length_km": 0.0,
      "bridge_length_km": 0.0,
      "existing_road_access_length_km": 0.0,
      "existing_road_access_percent": 0.0,
      "route_generation_method": "failed",
      "river_crossing_count": 0,
      "failed_reason": "connection timeout expired\nMultiple connection attempts failed. All failures were:\n- host: 'localhost', port: '5432', hostaddr: '::1': connection timeout expired\n- host: 'localhost', port: '5432', hostaddr: '127.0.0.1': connection timeout expired"
    }
  },
  {
    "rank": 16,
    "route_id": "R016",
    "from_node_id": "N011",
    "to_node_id": "N021",
    "estimated_flow": 372691.0,
    "distance_saving_km": 0.0,
    "total_screen_cost": 0.0,
    "economic_score": 0.0,
    "summary": {
      "label": "MVP 예비 경제성 점수",
      "status": "failed",
      "straight_distance_km": 8.081,
      "assumed_existing_route_length_km": 10.505,
      "route_length_km": 0.0,
      "distance_saving_km": 0.0,
      "benefit_proxy": 0.0,
      "cost_per_flow_saving": null,
      "surface_road_length_km": 0.0,
      "existing_road_length_km": 0.0,
      "existing_tunnel_length_km": 0.0,
      "new_surface_road_length_km": 0.0,
      "tunnel_length_km": 0.0,
      "bridge_length_km": 0.0,
      "existing_road_access_length_km": 0.0,
      "existing_road_access_percent": 0.0,
      "route_generation_method": "failed",
      "river_crossing_count": 0,
      "failed_reason": "connection timeout expired\nMultiple connection attempts failed. All failures were:\n- host: 'localhost', port: '5432', hostaddr: '::1': connection timeout expired\n- host: 'localhost', port: '5432', hostaddr: '127.0.0.1': connection timeout expired"
    }
  },
  {
    "rank": 17,
    "route_id": "R017",
    "from_node_id": "N024",
    "to_node_id": "N040",
    "estimated_flow": 362954.6,
    "distance_saving_km": 0.0,
    "total_screen_cost": 0.0,
    "economic_score": 0.0,
    "summary": {
      "label": "MVP 예비 경제성 점수",
      "status": "failed",
      "straight_distance_km": 15.95,
      "assumed_existing_route_length_km": 20.735,
      "route_length_km": 0.0,
      "distance_saving_km": 0.0,
      "benefit_proxy": 0.0,
      "cost_per_flow_saving": null,
      "surface_road_length_km": 0.0,
      "existing_road_length_km": 0.0,
      "existing_tunnel_length_km": 0.0,
      "new_surface_road_length_km": 0.0,
      "tunnel_length_km": 0.0,
      "bridge_length_km": 0.0,
      "existing_road_access_length_km": 0.0,
      "existing_road_access_percent": 0.0,
      "route_generation_method": "failed",
      "river_crossing_count": 0,
      "failed_reason": "connection timeout expired\nMultiple connection attempts failed. All failures were:\n- host: 'localhost', port: '5432', hostaddr: '::1': connection timeout expired\n- host: 'localhost', port: '5432', hostaddr: '127.0.0.1': connection timeout expired"
    }
  },
  {
    "rank": 18,
    "route_id": "R018",
    "from_node_id": "N024",
    "to_node_id": "N037",
    "estimated_flow": 356516.4,
    "distance_saving_km": 0.0,
    "total_screen_cost": 0.0,
    "economic_score": 0.0,
    "summary": {
      "label": "MVP 예비 경제성 점수",
      "status": "failed",
      "straight_distance_km": 15.02,
      "assumed_existing_route_length_km": 19.526,
      "route_length_km": 0.0,
      "distance_saving_km": 0.0,
      "benefit_proxy": 0.0,
      "cost_per_flow_saving": null,
      "surface_road_length_km": 0.0,
      "existing_road_length_km": 0.0,
      "existing_tunnel_length_km": 0.0,
      "new_surface_road_length_km": 0.0,
      "tunnel_length_km": 0.0,
      "bridge_length_km": 0.0,
      "existing_road_access_length_km": 0.0,
      "existing_road_access_percent": 0.0,
      "route_generation_method": "failed",
      "river_crossing_count": 0,
      "failed_reason": "connection timeout expired\nMultiple connection attempts failed. All failures were:\n- host: 'localhost', port: '5432', hostaddr: '::1': connection timeout expired\n- host: 'localhost', port: '5432', hostaddr: '127.0.0.1': connection timeout expired"
    }
  },
  {
    "rank": 19,
    "route_id": "R019",
    "from_node_id": "N043",
    "to_node_id": "N050",
    "estimated_flow": 352864.8,
    "distance_saving_km": 0.0,
    "total_screen_cost": 0.0,
    "economic_score": 0.0,
    "summary": {
      "label": "MVP 예비 경제성 점수",
      "status": "failed",
      "straight_distance_km": 7.76,
      "assumed_existing_route_length_km": 10.088,
      "route_length_km": 0.0,
      "distance_saving_km": 0.0,
      "benefit_proxy": 0.0,
      "cost_per_flow_saving": null,
      "surface_road_length_km": 0.0,
      "existing_road_length_km": 0.0,
      "existing_tunnel_length_km": 0.0,
      "new_surface_road_length_km": 0.0,
      "tunnel_length_km": 0.0,
      "bridge_length_km": 0.0,
      "existing_road_access_length_km": 0.0,
      "existing_road_access_percent": 0.0,
      "route_generation_method": "failed",
      "river_crossing_count": 0,
      "failed_reason": "connection timeout expired\nMultiple connection attempts failed. All failures were:\n- host: 'localhost', port: '5432', hostaddr: '::1': connection timeout expired\n- host: 'localhost', port: '5432', hostaddr: '127.0.0.1': connection timeout expired"
    }
  },
  {
    "rank": 20,
    "route_id": "R020",
    "from_node_id": "N005",
    "to_node_id": "N026",
    "estimated_flow": 346341.0,
    "distance_saving_km": 0.0,
    "total_screen_cost": 0.0,
    "economic_score": 0.0,
    "summary": {
      "label": "MVP 예비 경제성 점수",
      "status": "failed",
      "straight_distance_km": 7.791,
      "assumed_existing_route_length_km": 10.128,
      "route_length_km": 0.0,
      "distance_saving_km": 0.0,
      "benefit_proxy": 0.0,
      "cost_per_flow_saving": null,
      "surface_road_length_km": 0.0,
      "existing_road_length_km": 0.0,
      "existing_tunnel_length_km": 0.0,
      "new_surface_road_length_km": 0.0,
      "tunnel_length_km": 0.0,
      "bridge_length_km": 0.0,
      "existing_road_access_length_km": 0.0,
      "existing_road_access_percent": 0.0,
      "route_generation_method": "failed",
      "river_crossing_count": 0,
      "failed_reason": "connection timeout expired\nMultiple connection attempts failed. All failures were:\n- host: 'localhost', port: '5432', hostaddr: '::1': connection timeout expired\n- host: 'localhost', port: '5432', hostaddr: '127.0.0.1': connection timeout expired"
    }
  }
]